MANIFEST.in
setup.py
cerebrod.egg-info/PKG-INFO
cerebrod.egg-info/SOURCES.txt
cerebrod.egg-info/dependency_links.txt
cerebrod.egg-info/entry_points.txt
cerebrod.egg-info/requires.txt
cerebrod.egg-info/top_level.txt
cerebrod.egg-info/zip-safe
src/clusterconsole/main.py
src/clustersitter/__init__.py
src/clustersitter/actions.py
src/clustersitter/clusterstate.py
src/clustersitter/clusterstats.py
src/clustersitter/datarecord.py
src/clustersitter/deploymentrecipe.py
src/clustersitter/dnsprovider.py
src/clustersitter/dreamhost.py
src/clustersitter/dynect.py
src/clustersitter/eventmanager.py
src/clustersitter/jobfiller.py
src/clustersitter/machineconfig.py
src/clustersitter/machinemonitor.py
src/clustersitter/main.py
src/clustersitter/manage.py
src/clustersitter/monitoredmachine.py
src/clustersitter/productionjob.py
src/clustersitter/settings.py
src/clustersitter/sitter.py
src/clustersitter/urls.py
src/clustersitter/providers/__init__.py
src/clustersitter/providers/aws.py
src/clustersitter/providers/machineprovider.py
src/machineconsole/__init__.py
src/machineconsole/main.py
src/machineconsole/menu.py
src/machinesitter/__init__.py
src/machinesitter/machinemanager.py
src/machinesitter/machinestats.py
src/machinesitter/main.py
src/machinesitter/taskmanager.py
src/sittercommon/__init__.py
src/sittercommon/address.py
src/sittercommon/api.py
src/sittercommon/arg_parser.py
src/sittercommon/http_monitor.py
src/sittercommon/logmanager.py
src/sittercommon/machinedata.py
src/sittercommon/templates/cluster_overview.html
src/sittercommon/templates/index.html
src/sittercommon/templates/logs.html
src/sittercommon/templates/stats.html
src/sittercommon/utils/__init__.py
src/sittercommon/utils/change_debug_level.py
src/sittercommon/utils/list_jobs.py
src/sittercommon/utils/list_machines.py
src/sittercommon/utils/login.py
src/sittercommon/utils/main.py
src/sittercommon/utils/update_idle_limit.py
src/sittercommon/utils/update_job.py
src/sittercommon/utils/update_job_cfg.py
src/tasksitter/__init__.py
src/tasksitter/constraints.py
src/tasksitter/main.py
src/tasksitter/process.py
src/tasksitter/process_harness.py
src/tasksitter/stats_collector.py
test/test_basic.py
test/test_http_monitoring.py