Metadata-Version: 1.0
Name: cerebrod
Version: 1.2.9
Summary: A Cluster Management System
Home-page: http://zachgoldberg.com/
Author: Zach Goldberg
Author-email: zach@zachgoldberg.com
License: UNKNOWN
Download-URL: https://github.com/ZachGoldberg/Cerebro
Platform: UNKNOWN
